<?xml version = '1.0' encoding = 'UTF-8'?>
<DataTypesDesign class="oracle.dbtools.crest.model.design.datatypes.DataTypesDesign" name="DataTypes" id="4C00BA0B-A0D4-A9CC-5BDD-78AA433E30C6" mainViewID="4E2CB51A-A4FF-7074-81D9-01599849EAE7">
<createdBy>yeiso</createdBy>
<createdTime>2022-07-09 21:02:01 UTC</createdTime>
<ownerDesignName>Diagrama Ecommerce-DB</ownerDesignName>
<shouldBeOpen>false</shouldBeOpen>
<collectionOfRefsPrefix>array_ref_</collectionOfRefsPrefix>
<collectionPrefix>array_</collectionPrefix>
<defaultArrayLimit>10</defaultArrayLimit>
<defaultCollectionType_Kind>ARRAY</defaultCollectionType_Kind>
<defaultCollectionType_Suffix>_Array</defaultCollectionType_Suffix>
<embeddedStructuredTypePrefix>inst_</embeddedStructuredTypePrefix>
<referencePrefix>ref_</referencePrefix>
<useRoleInAssociationEndAsName>true</useRoleInAssociationEndAsName>
</DataTypesDesign>